Workbook

Sheet Improvement
A1: Previous Work Attributes | C1: Attributes after Interviews | E1: Attributes after Explanatory Survey + Text Analysis
A2: Accessibility/Public Transportation | C2: Distinctive local cuisine | E2: Diversity of authentic local restaurants
A3: Accessible Prices | C3: Heritage ambience of the historic center | E3: Heritage ambience of the historic center
A4: Accomodation availability | C4: Availability of museums and art venues | E4: Availability of museums and art venues
A5: Food | C5: Frequency of cultural events | E5: Availability of centrally located accommodation
A6: Historical background | C6: Proximity to natural areas | E6: Proximity to natural areas or outdoor routes
A7: Local events | C7: Ease of reaching the city by public transport | E7: City located outside major tourist circuits | F7: Replaced "Ease of reaching the city by public transport" as overtourism was an interesting attribute, and also can refer to the idea of proximity to other cities (move around to avoid crowd).
A8: Landscape | C8: Digital information availability | E8: Availability of tourist information (digital and on-site)
A9: Availability of tourists' packs | C9: Accommodation type | E9: Accommodation services (flexible cancellation, digital check-in, ammenities, etc)
C10: Quality of accommodation options | E10: Flexible scheduling of guided tours
C11: Accessibility to touristic points | E11: Density of touristic attractions within walking distance

Sheet Final Attirbutes
A1: Attribute | B1: Comments
A2: Diversity of authentic local restaurants | B2: Improved, and also includes the idea of "restaurants"
A3: Availability of museums and art venues | B3: This was always mentioned in the different analysis
A4: Heritage ambience of the historic center | B4: This includes all those comments related to historic and central buildings and atmosphere
A5: Ease of reaching the city by public transport | B5: Accesbility and transportation was frequently mentioned inf different ocations and in different ways. "Public" was added to avoid ambuiguity between those who prefer private from thsoe who prefer public transport.
A6: Proximity to natural areas or outdoor routes | B6: Added "outdoor routres" as some cases mentioned hikking/trekking activities
A7: Availability of centrally located accommodation | B7: This combines the need of being near the center and the distance of the accommodation
A8: Accommodation services (flexible cancellation, digital check-in, ammenities, etc) | B8: This includes quality/price of accommodation, as more services tend to be more expensive or higher quality
A9: Availability of tourist information (digital and on-site) | B9: This refers to information available previous and during the trip (blogs, comuna, and even info points)
A10: Flexible scheduling of guided tours | B10: At the end, I can say that this attribute was not frequent but always appeared in each stage of the analysis. Combines the need of guided tours to know better the city, with the need or having a flexbile and organsied itinerary.
A11: Density of touristic attractions within walking distance | B11: Added the idea of "walkable" as most respondents mentioned the idea of walking or using public transport

Sheet Short Survey - ChatGPT
A1: Attribute | B1: Observation
A2: Centrally located accommodations. | B2: Already in previous attributes
A3: Accommodation within walking distance to key attractions. | B3: Already in previous attributes
A4: Accommodation's high quality (4/5 stars). | B4: Already in previous attributes
A5: Flexible booking options (free cancellation, easy date change). | B5: Already in previous attributes
A6: Accommodation near daily essentials (supermarket, pharmacy, ATM). | B6: Already in previous attributes
A7: Accommodation services (24h check-in or digital self check-in). | B7: Already in previous attributes
A8: Availability of authentic local restaurants with regional dishes. | B8: Already in previous attributes
A9: Restaurants with online or advance booking. | B9: This is interesting, but should check if is relevant to include, taking into account that I already have something about restaruants.
A10: Availability of local food markets/craft fairs. | B10: Interesting, also saw this, but not mentioned by many tourists previously.
A11: Availability of traditional, family-run restaurants. | B11: This is also interesting, but again, related to local cuisine.
A12: Possibility of cultural immersion (local rituals, traditions, or workshops). | B12: Already in previous attributes
... A24: Availabilkity of luggage storage near stations or airports. | B24: This is really interesting attribute, yet it was not mentioned too much, and other attributes are more representative.

Sheet Short Survey - Analysis
A1: Attribute | B1: Observations
A2: Centrally located accommodation | B2: Already in previous attributes
A3: Accommodation near public transport | B3: Already in previous attributes
A4: Noise-exposure. | B4: New attribute, interesting, but yet for defining 10 there are more representative cases.
A5: Accesbility to beaches | B5: Already in previous attributes
A6: Late check-in | B6: Interesting attribute, can be associated to accommodation services.
A7: Ammenities (AC power, water pressure, mattress, blackout curtains). | B7: Already in previous attributes
A8: No hidden fees | B8: Interesting , but yet can be combined with online information, and also this to some extent is not managable by the city.
A9: Updated online information | B9: Already in previous attributes
A10: Touristic packages | B10: This is interesting, and can be related to better organization and provide activities.
A11: Authentic regional restaurants | B11: Already in previous attributes
A12: Heritage routes | B12: Can be combined with the Heritage ambience of the historic center
... A21: Overtorusim | B21: Mentioned once in the interviews, and an intresting attribute

Sheet Interview Attributes
A1: Attribute
A2: Distinctive local cuisine
A3: Heritage ambience of the historic center
A4: Availability of museums and art venues
A5: Frequency of cultural events
A6: Proximity to natural areas
A7: Ease of reaching the city by public transport
A8: Digital information availability
A9: Accommodation type
A10: Quality of accommodation options
A11: Accessibility to touristic points

Sheet ChatGPT Attributes Refined
A1: Attribute | B1: Definition for survey | C1: Observation
A2: Quality of local cuisine | B2: Perceived taste, variety, and authenticity of local food (typical dishes, local products). | C2: Quality is a characteristic a bit difficult to manage by the city, it depends on each restaurant. But clearly the food, and mainly in Italy is an important attribute that MUST be in the list. Should be redefined.
A3: Presence of heritage architecture | B3: Existence and visibility of preserved historical buildings, monuments, and landmarks.
A4: Ambience of the historic center | B4: Overall atmosphere, aesthetics, and cultural feeling of old-town areas (walkability, charm). | C4: This could be combined with the previous one.
A5: Availability of museums and art venues | B5: Number and accessibility of museums, galleries, or artistic spaces.
A6: Frequency of cultural events | B6: Availability of traditional festivals, parades, concerts, or local celebrations during the visit. | C6: This is stationality, and depends on when it is the event, and can't be managed more than for that specific period (as Quintana).
A7: Quality of natural scenery | B7: Appeal and conservation of surrounding natural landscapes (parks, hills, beaches).
A8: Friendliness of local residents | B8: Degree of hospitality, helpfulness, and welcoming attitude of locals toward visitors. | C8: Friendliness is complicated to managed, I prefer more actionable attributes.
A9: Cleanliness and orderliness of the city | B9: Perceived hygiene, maintenance, and visual order of public spaces. | C9: Although is an intresting attribute for a city, yet it was not a frequent topic mentioned.
A10: Authenticity of local experience | B10: Perception that experiences are genuine and culturally rooted (not overly commercial). | C10: This could be complement with local cuisine.
A11: Availability of guided tours and information on-site | B11: Presence and usefulness of local tours, guides, or interpretive materials. | C11: This is an intresting attribute, yet is not too frequent, it could be analyze in future approaches.
A12: Attractiveness of main squares and public spaces | B12: Visual and social appeal of plazas, piazzas, and outdoor gathering places. | C12: This could be combined with 2nd and 3rd
A13: Ease of access from other destinations | B13: Travel time, routes, and overall convenience to reach the city.
A14: Cost and comfort of transport connections | B14: Perceived affordability and comfort of transportation to and within the destination. | C14: This can be combined with previous attribute.
A15: Quality of accommodation options | B15: Variety, cleanliness, comfort, and adequacy of available lodgings.
A16: Usefulness of online information | B16: Clarity, accuracy, and trustworthiness of online travel resources used for planning (TripAdvisor, ChatGPT, etc.). | C16: This could be interesting, but also include on-site information. Information is important in tourism experiences, and although opinions or recommendations are not managable, yes it is the information online (such as comuna's web page, presence in google maps, trip blogs, etc)
A17: Scale and diversity of attractions | B17: Perception of the city’s size and richness of things to see/do.
A18: Affordability of the destination | B18: General perception of whether the place is expensive or budget-friendly. | C18: This could be a bit general, and tested with Van Westendorp model.
A19: Availability of visitor services | B19: Access to everyday facilities like supermarkets, pharmacies, or ATMs. | C19: This was mentioned just by 1 person

Sheet ChatGPT Attributes
A1: Attribute (English) | B1: Frequency | C1: Interviews where mentioned
A2: Local food / gastronomy | B2: 10 | C2: 1, 2, 3, 4, 5, 6, 7, 8, 9, 10
A3: Architecture / historical buildings | B3: 9 | C3: 1, 2, 3, 4, 5, 6, 7, 9, 10
A4: Museums / art exhibitions | B4: 7 | C4: 1, 2, 4, 6, 8, 9, 10
A5: Cultural festivals / events | B5: 7 | C5: 1, 4, 5, 6, 7, 8, 10
A6: City atmosphere / vibe / livability | B6: 6 | C6: 1, 2, 3, 6, 7, 8
A7: Traditional restaurants / family-run eateries | B7: 6 | C7: 3, 4, 6, 7, 9, 10
A8: Historic centers / old towns | B8: 5 | C8: 2, 4, 5, 9, 10
A9: Local people friendliness / hospitality | B9: 5 | C9: 3, 4, 6, 7, 10
A10: Cleanliness of the city | B10: 4 | C10: 3, 4, 6, 7
A11: Artistic heritage / Renaissance art | B11: 4 | C11: 2, 5, 8, 10
A12: Squares / piazzas / public spaces | B12: 4 | C12: 4, 7, 8, 10
A13: Natural landscapes / vegetation / parks | B13: 3 | C13: 4, 6, 7
... A21: Scenic views / viewpoints / aesthetic beauty | B21: 2 | C21: 6, 7

Sheet Attribute_Frequency_Table
A1: # | B1: Attribute | C1: Frequency | D1: Personal Observation
A2: 1 | B2: =+VLOOKUP($A2,Attributes_by_Interview!$A:$C,2,0) -> accommodation type | C2: =+VLOOKUP($A2,Attributes_by_Interview!$A:$C,3,0) -> 9 | D2: Related to accommodation. This case can confusing and ambiguous. I should improve this attribute.
A3: =+A2+1 -> 2 | B3: =+VLOOKUP($A3,Attributes_by_Interview!$A:$C,2,0) -> online recommendations | C3: =+VLOOKUP($A3,Attributes_by_Interview!$A:$C,3,0) -> 9 | D3: This attribute should be re-think, as this attribute cannot be totally developed by a city, is not in their scope. Maybe the information online can be in a city's scope and possible to work on.
A4: =+A3+1 -> 3 | B4: =+VLOOKUP($A4,Attributes_by_Interview!$A:$C,2,0) -> proximity to other destinations | C4: =+VLOOKUP($A4,Attributes_by_Interview!$A:$C,3,0) -> 9 | D4: Proximity to other destinations
A5: =+A4+1 -> 4 | B5: =+VLOOKUP($A5,Attributes_by_Interview!$A:$C,2,0) -> local cuisine | C5: =+VLOOKUP($A5,Attributes_by_Interview!$A:$C,3,0) -> 8 | D5: Local cuisine. This is a little bit general, could be clearer, and avoid ambuiguity.
A6: =+A5+1 -> 5 | B6: =+VLOOKUP($A6,Attributes_by_Interview!$A:$C,2,0) -> accessibility to touristic points | C6: =+VLOOKUP($A6,Attributes_by_Interview!$A:$C,3,0) -> 7 | D6: Accessibility
A7: =+A6+1 -> 6 | B7: =+VLOOKUP($A7,Attributes_by_Interview!$A:$C,2,0) -> cost to reach | C7: =+VLOOKUP($A7,Attributes_by_Interview!$A:$C,3,0) -> 7 | D7: Distance to reach
A8: =+A7+1 -> 7 | B8: =+VLOOKUP($A8,Attributes_by_Interview!$A:$C,2,0) -> accommodation price | C8: =+VLOOKUP($A8,Attributes_by_Interview!$A:$C,3,0) -> 6 | D8: Related to accommodation.
A9: =+A8+1 -> 8 | B9: =+VLOOKUP($A9,Attributes_by_Interview!$A:$C,2,0) -> distance to reach | C9: =+VLOOKUP($A9,Attributes_by_Interview!$A:$C,3,0) -> 6 | D9: Distance to reach. Should be clearer, and avoid ambuiguity and overlapping with other cases.
A10: =+A9+1 -> 9 | B10: =+VLOOKUP($A10,Attributes_by_Interview!$A:$C,2,0) -> historical buildings | C10: =+VLOOKUP($A10,Attributes_by_Interview!$A:$C,3,0) -> 6 | D10: Historical places
A11: =+A10+1 -> 10 | B11: =+VLOOKUP($A11,Attributes_by_Interview!$A:$C,2,0) -> local events | C11: =+VLOOKUP($A11,Attributes_by_Interview!$A:$C,3,0) -> 6 | D11: Local events
A12: =+A11+1 -> 11 | B12: =+VLOOKUP($A12,Attributes_by_Interview!$A:$C,2,0) -> accommodation services | C12: =+VLOOKUP($A12,Attributes_by_Interview!$A:$C,3,0) -> 5 | D12: Related to accommodation.
A13: =+A12+1 -> 12 | B13: =+VLOOKUP($A13,Attributes_by_Interview!$A:$C,2,0) -> availability of transport to destination | C13: =+VLOOKUP($A13,Attributes_by_Interview!$A:$C,3,0) -> 5 | D13: Accessibility. This is ambiguous, as someone who prfers private transport may answer identical as someone who prefers public transport.
A14: =+A13+1 -> 13 | B14: =+VLOOKUP($A14,Attributes_by_Interview!$A:$C,2,0) -> cultural immersion | C14: =+VLOOKUP($A14,Attributes_by_Interview!$A:$C,3,0) -> 5 | D14: This is a bit general, could be improved.
... A44: =+A43+1 -> 43 | B44: =+VLOOKUP($A44,Attributes_by_Interview!$A:$C,2,0) -> music events cost | C44: =+VLOOKUP($A44,Attributes_by_Interview!$A:$C,3,0) -> 1 | D44: Local events
A45: =+A44+1 -> 44 | B45: =+VLOOKUP($A45,Attributes_by_Interview!$A:$C,2,0) -> supermarket availability | C45: =+VLOOKUP($A45,Attributes_by_Interview!$A:$C,3,0) -> 1

Sheet Attributes_by_Interview
A1: # | B1: Attribute | C1: Total | D1: Interview 1 | E1: Interview 2 | F1: Interview 3 | G1: Interview 4 | H1: Interview 5 | I1: Interview 6 | J1: Interview 7 | K1: Interview 8 | L1: Interview 9 | M1: Interview 10
A2: =+IF(COUNTIF($C$1:C1,C2)>0,RANK(C2,$C$2:$C$45,0)+COUNTIF($C$1:C1,C2),RANK(C2,$C$2:$C$45,0)) -> 20 | B2: access to beaches | C2: =+SUM(D2:M2) -> 3 | D2: 0 | E2: 1 | F2: 1 | G2: 1 | H2: 0 | I2: 0 | J2: 0 | K2: 0 | L2: 0 | M2: 0
A3: =+IF(COUNTIF($C$1:C2,C3)>0,RANK(C3,$C$2:$C$45,0)+COUNTIF($C$1:C2,C3),RANK(C3,$C$2:$C$45,0)) -> 33 | B3: access to mountains | C3: =+SUM(D3:M3) -> 1 | D3: 0 | E3: 0 | F3: 0 | G3: 1 | H3: 0 | I3: 0 | J3: 0 | K3: 0 | L3: 0 | M3: 0
A4: =+IF(COUNTIF($C$1:C3,C4)>0,RANK(C4,$C$2:$C$45,0)+COUNTIF($C$1:C3,C4),RANK(C4,$C$2:$C$45,0)) -> 5 | B4: accessibility to touristic points | C4: =+SUM(D4:M4) -> 7 | D4: 1 | E4: 1 | F4: 0 | G4: 1 | H4: 1 | I4: 0 | J4: 1 | K4: 0 | L4: 1 | M4: 1
A5: =+IF(COUNTIF($C$1:C4,C5)>0,RANK(C5,$C$2:$C$45,0)+COUNTIF($C$1:C4,C5),RANK(C5,$C$2:$C$45,0)) -> 25 | B5: accessible by public transport | C5: =+SUM(D5:M5) -> 2 | D5: 1 | E5: 0 | F5: 0 | G5: 0 | H5: 0 | I5: 0 | J5: 0 | K5: 1 | L5: 0 | M5: 0
A6: =+IF(COUNTIF($C$1:C5,C6)>0,RANK(C6,$C$2:$C$45,0)+COUNTIF($C$1:C5,C6),RANK(C6,$C$2:$C$45,0)) -> 16 | B6: accommodation location | C6: =+SUM(D6:M6) -> 4 | D6: 1 | E6: 1 | F6: 0 | G6: 0 | H6: 0 | I6: 0 | J6: 0 | K6: 0 | L6: 1 | M6: 1
A7: =+IF(COUNTIF($C$1:C6,C7)>0,RANK(C7,$C$2:$C$45,0)+COUNTIF($C$1:C6,C7),RANK(C7,$C$2:$C$45,0)) -> 7 | B7: accommodation price | C7: =+SUM(D7:M7) -> 6 | D7: 0 | E7: 0 | F7: 1 | G7: 1 | H7: 0 | I7: 1 | J7: 1 | K7: 1 | L7: 1 | M7: 0
A8: =+IF(COUNTIF($C$1:C7,C8)>0,RANK(C8,$C$2:$C$45,0)+COUNTIF($C$1:C7,C8),RANK(C8,$C$2:$C$45,0)) -> 26 | B8: accommodation quality | C8: =+SUM(D8:M8) -> 2 | D8: 0 | E8: 0 | F8: 1 | G8: 0 | H8: 0 | I8: 0 | J8: 0 | K8: 1 | L8: 0 | M8: 0
A9: =+IF(COUNTIF($C$1:C8,C9)>0,RANK(C9,$C$2:$C$45,0)+COUNTIF($C$1:C8,C9),RANK(C9,$C$2:$C$45,0)) -> 11 | B9: accommodation services | C9: =+SUM(D9:M9) -> 5 | D9: 0 | E9: 1 | F9: 1 | G9: 0 | H9: 1 | I9: 0 | J9: 1 | K9: 0 | L9: 0 | M9: 1
A10: =+IF(COUNTIF($C$1:C9,C10)>0,RANK(C10,$C$2:$C$45,0)+COUNTIF($C$1:C9,C10),RANK(C10,$C$2:$C$45,0)) -> 1 | B10: accommodation type | C10: =+SUM(D10:M10) -> 9 | D10: 1 | E10: 1 | F10: 1 | G10: 1 | H10: 0 | I10: 1 | J10: 1 | K10: 1 | L10: 1 | M10: 1
A11: =+IF(COUNTIF($C$1:C10,C11)>0,RANK(C11,$C$2:$C$45,0)+COUNTIF($C$1:C10,C11),RANK(C11,$C$2:$C$45,0)) -> 34 | B11: attraction availability | C11: =+SUM(D11:M11) -> 1 | D11: 0 | E11: 0 | F11: 0 | G11: 0 | H11: 1 | I11: 0 | J11: 0 | K11: 0 | L11: 0 | M11: 0
A12: =+IF(COUNTIF($C$1:C11,C12)>0,RANK(C12,$C$2:$C$45,0)+COUNTIF($C$1:C11,C12),RANK(C12,$C$2:$C$45,0)) -> 35 | B12: availability of city tours | C12: =+SUM(D12:M12) -> 1 | D12: 0 | E12: 0 | F12: 0 | G12: 0 | H12: 0 | I12: 0 | J12: 0 | K12: 0 | L12: 1 | M12: 0
A13: =+IF(COUNTIF($C$1:C12,C13)>0,RANK(C13,$C$2:$C$45,0)+COUNTIF($C$1:C12,C13),RANK(C13,$C$2:$C$45,0)) -> 12 | B13: availability of transport to destination | C13: =+SUM(D13:M13) -> 5 | D13: 0 | E13: 0 | F13: 0 | G13: 0 | H13: 1 | I13: 1 | J13: 1 | K13: 0 | L13: 1 | M13: 1
... A45: =+IF(COUNTIF($C$1:C44,C45)>0,RANK(C45,$C$2:$C$45,0)+COUNTIF($C$1:C44,C45),RANK(C45,$C$2:$C$45,0)) -> 32 | B45: variety of hours for transportation | C45: =+SUM(D45:M45) -> 2 | D45: 0 | E45: 0 | F45: 0 | G45: 0 | H45: 0 | I45: 0 | J45: 0 | K45: 0 | L45: 1 | M45: 1
